LICENSE.txt
MANIFEST.in
expose.py
setup.cfg
setup.py
modelstruct.egg-info/PKG-INFO
modelstruct.egg-info/SOURCES.txt
modelstruct.egg-info/dependency_links.txt
modelstruct.egg-info/pbr.json
modelstruct.egg-info/requires.txt
modelstruct.egg-info/top_level.txt