Metadata-Version: 1.1
Name: modelstruct
Version: 1.0.0
Summary: A module to expose the structure of SQLAlchemy models as a RESTful API
Home-page: https://github.com/mathur/modelstruct
Author: Rohan Mathur
Author-email: rohan@rmathur.com
License: MIT
Keywords: sqlalchemy models structure expose api
Platform: UNKNOWN
Classifier: Development Status :: 3 - Alpha
Classifier: Intended Audience :: Developers
Classifier: Topic :: Software Development :: Build Tools
Classifier: License :: OSI Approved :: MIT License
Classifier: Programming Language :: Python :: 2
Classifier: Programming Language :: Python :: 2.6
Classifier: Programming Language :: Python :: 2.7
